MANIFEST.in
README.rst
setup.py
job_runner_ws_server/__init__.py
job_runner_ws_server/events.py
job_runner_ws_server/runner.py
job_runner_ws_server/websockets.py
job_runner_ws_server.egg-info/PKG-INFO
job_runner_ws_server.egg-info/SOURCES.txt
job_runner_ws_server.egg-info/dependency_links.txt
job_runner_ws_server.egg-info/requires.txt
job_runner_ws_server.egg-info/top_level.txt
scripts/job_runner_ws_server