Metadata-Version: 1.0
Name: job-runner-ws-server
Version: 1.0.0
Summary: Job-Runner WebSocket Server
Home-page: https://github.com/spilgames/job_runner_ws_server/
Author: Orne Brocaar
Author-email: orne.brocaar@spilgames.com
License: UNKNOWN
Platform: UNKNOWN
